fast_files/VERSION
fast_files/__init__.py
fast_files/arguments.yaml
fast_files/fast_files.py
fast_files-0.0.2.dist-info/LICENSE
fast_files-0.0.2.dist-info/METADATA
fast_files-0.0.2.dist-info/WHEEL
fast_files-0.0.2.dist-info/entry_points.txt
fast_files-0.0.2.dist-info/top_level.txt
fast_files-0.0.2.dist-info/RECORD
