Metadata-Version: 2.1
Name: fast-files
Version: 0.0.2
Summary: Serve static files with fastapi.
Home-page: https://github.com/alphabet5/fastapi-file-server
Author: John Burt
Author-email: johnburt.jab@gmail.com
License: UNKNOWN
Platform: UNKNOWN
Classifier: Programming Language :: Python :: 3
Classifier: License :: OSI Approved :: Apache Software License
Classifier: Operating System :: OS Independent
Requires-Python: >=3.8
Requires-Dist: fastapi
Requires-Dist: uvicorn
Requires-Dist: aiofiles
Requires-Dist: yamlarg
Requires-Dist: pyyaml
